[
  {
    "id": 1,
    "name": "Bruce Willis",
    "age": 60,
    "job": {
        "company": "XX centuries fox"
    },
    "address": {
        "addres": "East 52d street, 308",
        "city": "NYC",
        "country": "USA"
    }
  },
  {
    "id": 2,
    "name": "James Bond",
    "age": 52,
    "job": {
        "company": "Swiss Bank",
        "address": {
        	"address": "Zuricher Platz, 5",
        	"city": "Zurich",
        	"country": "Switzerland"
        }
    },
    "address": {
        "addres": "Blumen Strasse, 54",
        "city": "Zurich",
        "country": "Switzerland",
        "zipcode": "CH-2087"
    }
  },
  {
    "id": 3,
    "name": "Jane Bond",
    "age": 34,
    "job": {
        "company": "Swiss Bank",
        "address": {
        	"address": "Zuricher Platz, 5",
        	"city": "Zurich",
        	"country": "Switzerland"
        }
    },
    "address": {
        "addres": "Blumen Strasse, 54",
        "city": "Zurich",
        "country": "Switzerland",
        "zipcode": "CH-2087"
    }
  }
]